Btc_price1/Btc_price.py
Btc_price1/__init__.py
Btc_price1-0.1.4.dist-info/LICENSE.txt
Btc_price1-0.1.4.dist-info/METADATA
Btc_price1-0.1.4.dist-info/WHEEL
Btc_price1-0.1.4.dist-info/top_level.txt
Btc_price1-0.1.4.dist-info/RECORD
